force_kill/__init__.py
force_kill/force_kill.py
force_kill-0.0.2.dist-info/METADATA
force_kill-0.0.2.dist-info/WHEEL
force_kill-0.0.2.dist-info/top_level.txt
force_kill-0.0.2.dist-info/RECORD
